seventv/__init__.py
seventv/seventv.py
seventv-2.4.0.dist-info/LICENSE
seventv-2.4.0.dist-info/METADATA
seventv-2.4.0.dist-info/WHEEL
seventv-2.4.0.dist-info/top_level.txt
seventv-2.4.0.dist-info/RECORD
