Metadata-Version: 2.1
Name: seventv
Version: 2.4.0
Summary: An asynchronous API-wrapper for 7tv.app
Home-page: https://github.com/probablyjassin/seventv.py
Author: Jässin Aouani
Author-email: jassin@aouani.de
License: GPL
Classifier: Programming Language :: Python :: 3
Classifier: Programming Language :: Python :: 3.6
Classifier: Programming Language :: Python :: 3.7
Classifier: Programming Language :: Python :: 3.8
Classifier: Programming Language :: Python :: 3.9
License-File: LICENSE
Requires-Dist: aiohttp
